{
	"name": "PL_if_condition_using metadata",
	"properties": {
		"activities": [
			{
				"name": "Get Metadata1",
				"type": "GetMetadata",
				"dependsOn": [],
				"policy": {
					"timeout": "0.12:00:00",
					"retry": 0,
					"retryIntervalInSeconds": 30,
					"secureOutput": false,
					"secureInput": false
				},
				"userProperties": [],
				"typeProperties": {
					"dataset": {
						"referenceName": "Emp_Input_dataset",
						"type": "DatasetReference"
					},
					"fieldList": [
						"columnCount"
					],
					"storeSettings": {
						"type": "AzureBlobStorageReadSettings",
						"recursive": true,
						"enablePartitionDiscovery": false
					},
					"formatSettings": {
						"type": "DelimitedTextReadSettings"
					}
				}
			},
			{
				"name": "If Condition1",
				"type": "IfCondition",
				"dependsOn": [
					{
						"activity": "Get Metadata1",
						"dependencyConditions": [
							"Succeeded"
						]
					}
				],
				"userProperties": [],
				"typeProperties": {
					"expression": {
						"value": "@activity('Get Metadata1').output.columnCount",
						"type": "Expression"
					},
					"ifFalseActivities": [
						{
							"name": "Set variable2",
							"type": "SetVariable",
							"dependsOn": [],
							"policy": {
								"secureOutput": false,
								"secureInput": false
							},
							"userProperties": [],
							"typeProperties": {
								"variableName": "y",
								"value": {
									"value": "'empty'",
									"type": "Expression"
								}
							}
						}
					],
					"ifTrueActivities": [
						{
							"name": "Set variable1",
							"type": "SetVariable",
							"dependsOn": [],
							"policy": {
								"secureOutput": false,
								"secureInput": false
							},
							"userProperties": [],
							"typeProperties": {
								"variableName": "x",
								"value": {
									"value": "@activity('Get Metadata1').output.columnCount",
									"type": "Expression"
								}
							}
						}
					]
				}
			}
		],
		"variables": {
			"x": {
				"type": "Integer"
			},
			"y": {
				"type": "String"
			}
		},
		"folder": {
			"name": "Control-Flow-Pipeline"
		},
		"annotations": [],
		"lastPublishTime": "2025-01-27T07:55:21Z"
	},
	"type": "Microsoft.DataFactory/factories/pipelines"
}